setup.py
npm/__init__.py
npm/bindings.py
npm/conf.py
npm/exceptions.py
npm/interrogate.py
npm.egg-info/PKG-INFO
npm.egg-info/SOURCES.txt
npm.egg-info/dependency_links.txt
npm.egg-info/top_level.txt
npm/utils/__init__.py
npm/utils/conf/__init__.py
npm/utils/six/__init__.py