Metadata-Version: 1.0
Name: npm
Version: 0.1.0
Summary: Python bindings and utils for npm.
Home-page: https://github.com/markfinger/python-npm
Author: Mark Finger
Author-email: markfinger@gmail.com
License: UNKNOWN
Platform: UNKNOWN
